pymage_size/__init__.py
pymage_size/pymage_size.py
pymage_size-1.7.1.dist-info/METADATA
pymage_size-1.7.1.dist-info/WHEEL
pymage_size-1.7.1.dist-info/LICENSE
pymage_size-1.7.1.dist-info/RECORD
