Metadata-Version: 2.1
Name: pymage-size
Version: 1.7.1
Summary: A Python package for getting the dimensions of an image without loading it into memory.
Home-page: https://github.com/kobaltcore/pymage_size
License: MIT
Author: cobaltcore
Author-email: cobaltcore@yandex.com
Requires-Python: >=3.9,<4.0
Classifier: License :: OSI Approved :: MIT License
Classifier: Programming Language :: Python :: 3
Classifier: Programming Language :: Python :: 3.9
Classifier: Programming Language :: Python :: 3.10
Classifier: Programming Language :: Python :: 3.11
Project-URL: Repository, https://github.com/kobaltcore/pymage_size
